eb_create_environment/__init__.py
eb_create_environment/database.py
eb_create_environment/default_config.yml
eb_create_environment/eb_setup.py
eb_create_environment/script.py
eb_create_environment/utils.py
eb_create_environment/vpc.py
eb_create_environment-0.2.0.dist-info/licenses/LICENSE
eb_create_environment-0.2.0.dist-info/METADATA
eb_create_environment-0.2.0.dist-info/WHEEL
eb_create_environment-0.2.0.dist-info/entry_points.txt
eb_create_environment-0.2.0.dist-info/top_level.txt
eb_create_environment-0.2.0.dist-info/RECORD
