Metadata-Version: 2.4
Name: eb-create-environment
Version: 0.2.0
Summary: Tool to create an Elastic Beanstalk environment and linked database using sensible defaults
Author-email: "Zagaran, Inc." <info@zagaran.com>
License-Expression: MIT
Project-URL: Homepage, https://github.com/zagaran/eb-environment-creation
Keywords: aws,eb,elastic,beanstalk,rds,database,create,environment
Classifier: Programming Language :: Python :: 3
Classifier: Operating System :: OS Independent
Requires-Python: >=3.8
License-File: LICENSE
Requires-Dist: boto3
Requires-Dist: choicesenum
Requires-Dist: ipython
Requires-Dist: jedi
Requires-Dist: pyyaml
Dynamic: license-file
